{"0002.png871":{"filename":"0002.png","size":871,"regions":[{"shape_attributes":{"name":"polyline","all_points_x":[65,67,68,70,73,76,77,75,71,68,66,66,66,66,64,64,64,63,62,60,57,56,55,54,53,55,57,60,62,63,63,65,65],"all_points_y":[64,61,59,57,56,57,60,64,64,64,64,65,67,69,68,66,65,65,66,67,67,66,65,64,62,60,59,59,61,63,64,63,64]},"region_attributes":{"name":"not_defined","type":"unknown","image_quality":{"good":true,"frontal":true,"good_illumination":true}}}],"file_attributes":{"caption":"","public_domain":"no","image_url":""}},"0003.png1195":{"filename":"0003.png","size":1195,"regions":[{"shape_attributes":{"name":"polyline","all_points_x":[65,66,68,71,74,76,78,78,75,71,68,67,65,65,68,69,69,68,66,63,62,63,64,64,62,60,57,53,50,51,54,57,59,61,62,64],"all_points_y":[62,60,57,54,54,54,56,59,63,64,63,63,64,66,67,68,71,73,73,72,68,66,66,65,65,65,67,66,63,60,58,58,59,61,63,63]},"region_attributes":{"type":"unknown","image_quality":{"good":true,"frontal":true,"good_illumination":true},"leaf":"not_defined"}}],"file_attributes":{"caption":"","public_domain":"no","image_url":""}},"0004.png1456":{"filename":"0004.png","size":1456,"regions":[{"shape_attributes":{"name":"polyline","all_points_x":[62,64,66,67,68,70,74,78,79,79,75,73,69,66,66,69,70,70,69,66,62,62,64,64,62,60,57,54,52,48,48,51,55,59,61,62],"all_points_y":[63,61,62,60,56,53,51,52,55,58,62,63,62,64,66,68,70,74,76,77,76,74,67,65,65,66,68,68,67,65,61,58,58,59,61,63]},"region_attributes":{"type":"unknown","image_quality":{"good":true,"frontal":true,"good_illumination":true},"leaf":"not_defined"}}],"file_attributes":{"caption":"","public_domain":"no","image_url":""}},"0005.png1621":{"filename":"0005.png","size":1621,"regions":[{"shape_attributes":{"name":"polyline","all_points_x":[62,62,62,63,64,64,65,67,68,69,70,74,76,79,80,80,78,76,73,70,66,65,66,68,70,71,71,71,69,66,63,62,61,63,63,63,61,58,55,51,48,48,49,51,56,58,60,62,62],"all_points_y":[62,61,59,59,59,61,62,60,57,54,52,51,51,51,52,55,59,61,62,62,63,63,64,67,69,72,76,78,80,80,78,77,74,70,66,64,64,66,67,66,65,62,59,58,57,59,61,62,62]},"region_attributes":{"type":"unknown","image_quality":{"good":true,"frontal":true,"good_illumination":true},"leaf":"not_defined"}}],"file_attributes":{"caption":"","public_domain":"no","image_url":""}},"0006.png2086":{"filename":"0006.png","size":2086,"regions":[{"shape_attributes":{"name":"polyline","all_points_x":[65,64,60,59,61,64,67,68,68,67,67,70,72,73,76,77,79,80,83,84,84,82,80,78,76,72,69,68,68,70,72,74,75,74,74,75,72,71,68,66,64,64,64,65,65,65,65,62,60,58,55,52,49,48,48,52,55,58,59,63,64],"all_points_y":[62,60,58,53,51,50,51,53,57,60,62,57,54,51,50,50,50,50,51,54,57,58,60,61,61,61,61,63,66,69,70,72,77,79,81,83,84,85,84,85,83,80,77,74,70,67,64,64,66,67,67,66,65,62,59,56,56,56,58,62,62]},"region_attributes":{"type":"unknown","image_quality":{"good":true,"frontal":true,"good_illumination":true},"leaf":"not_defined"}}],"file_attributes":{"caption":"","public_domain":"no","image_url":""}},"0007.png2588":{"filename":"0007.png","size":2588,"regions":[{"shape_attributes":{"name":"polyline","all_points_x":[64,64,62,60,57,57,58,64,66,68,68,69,69,67,68,72,73,75,77,79,80,83,86,86,83,81,79,77,75,72,69,68,68,70,73,75,76,76,75,73,71,67,63,62,62,63,65,65,65,65,64,61,59,56,53,49,47,48,49,51,55,58,60,62,64],"all_points_y":[62,60,58,56,55,52,46,43,43,45,46,50,54,61,61,58,53,52,51,50,50,50,54,57,60,61,61,62,62,62,62,64,66,68,70,73,75,78,82,84,87,88,86,84,80,77,73,70,66,64,63,64,66,67,67,65,63,59,57,56,56,56,58,61,62]},"region_attributes":{"type":"unknown","image_quality":{"good":true,"frontal":true,"good_illumination":true},"leaf":"not_defined"}}],"file_attributes":{"caption":"","public_domain":"no","image_url":""}},"0008.png2899":{"filename":"0008.png","size":2899,"regions":[{"shape_attributes":{"name":"polyline","all_points_x":[64,63,62,59,58,58,58,57,58,63,67,68,68,66,66,66,68,68,69,72,73,79,82,86,87,84,78,76,74,72,70,73,69,69,70,72,75,76,73,71,68,66,64,62,60,61,63,64,65,65,65,64,61,57,53,51,48,47,46,48,50,54,57,59,61,63,64],"all_points_y":[61,58,56,55,51,47,42,37,34,32,38,42,44,46,51,52,57,61,62,58,55,50,50,53,58,61,63,62,62,61,62,63,66,68,69,71,76,81,85,87,89,90,89,87,85,81,77,73,71,67,63,63,64,65,66,65,62,60,58,56,55,54,54,57,60,61,60]},"region_attributes":{"type":"unknown","image_quality":{"good":true,"frontal":true,"good_illumination":true},"leaf":"not_defined"}}],"file_attributes":{"caption":"","public_domain":"no","image_url":""}},"0009.png2872":{"filename":"0009.png","size":2872,"regions":[{"shape_attributes":{"name":"polyline","all_points_x":[61,59,58,53,53,53,54,54,56,59,60,61,61,61,61,62,62,65,65,65,68,70,71,77,81,83,84,81,77,76,74,72,68,67,66,73,71,68,63,60,57,59,61,62,62,57,53,48,45,44,46,48,51,55,61,61],"all_points_y":[63,59,57,56,52,47,39,36,32,32,35,40,43,46,49,53,56,58,61,63,63,60,58,54,55,58,61,64,64,65,69,69,69,68,70,77,84,88,90,89,86,81,76,70,65,66,67,67,66,61,58,57,57,58,63,62]},"region_attributes":{"type":"unknown","image_quality":{"good":true,"frontal":true,"good_illumination":true},"leaf":"not_defined"}}],"file_attributes":{"caption":"","public_domain":"no","image_url":""}},"0010.png3643":{"filename":"0010.png","size":3643,"regions":[{"shape_attributes":{"name":"polyline","all_points_x":[59,57,51,49,49,50,48,48,48,50,50,53,55,56,56,55,58,63,65,65,65,67,70,73,78,82,83,83,82,80,84,85,85,85,80,77,72,68,72,72,68,67,64,62,59,56,56,57,59,61,61,61,57,54,51,48,46,44,43,45,51,55,56,58,58,58],"all_points_y":[59,55,54,53,48,45,38,34,31,29,24,23,25,26,32,36,45,55,57,60,62,62,60,55,54,55,58,61,63,64,66,69,73,77,78,77,76,75,80,86,89,91,91,92,93,91,86,83,77,71,67,65,67,68,68,67,67,65,61,58,57,59,60,60,59,59]},"region_attributes":{"type":"unknown","image_quality":{"good":true,"frontal":true,"good_illumination":true},"leaf":"not_defined"}}],"file_attributes":{"caption":"","public_domain":"no","image_url":""}},"0015.png918":{"filename":"0015.png","size":918,"regions":[{"shape_attributes":{"name":"polyline","all_points_x":[64,64,64,63,62,61,58,56,57,59,61,62,64,63,61,59,59,60,61,62,64,67,67,65,65,67,68,68,67,65,64],"all_points_y":[62,59,55,54,53,51,51,54,58,60,61,62,63,65,66,68,71,73,74,75,75,71,68,65,64,64,64,62,61,62,62]},"region_attributes":{"type":"unknown","image_quality":{"good":true,"frontal":true,"good_illumination":true},"leaf":"not_defined"}}],"file_attributes":{"caption":"","public_domain":"no","image_url":""}},"0016.png1237":{"filename":"0016.png","size":1237,"regions":[{"shape_attributes":{"name":"polyline","all_points_x":[63,63,63,61,58,55,54,54,58,61,63,63,59,58,58,59,62,64,65,66,66,66,66,65,65,67,68,71,72,73,72,70,68,67,66,64,63],"all_points_y":[63,59,56,53,51,51,54,58,61,62,64,66,68,72,74,77,78,77,76,74,73,71,68,67,65,65,66,66,64,63,60,59,60,61,63,63,62]},"region_attributes":{"type":"unknown","image_quality":{"good":true,"frontal":true,"good_illumination":true},"leaf":"not_defined"}}],"file_attributes":{"caption":"","public_domain":"no","image_url":""}},"0017.png1471":{"filename":"0017.png","size":1471,"regions":[{"shape_attributes":{"name":"polyline","all_points_x":[64,62,62,61,58,55,53,52,53,55,58,60,61,61,63,61,58,58,58,61,65,67,67,67,66,65,67,71,76,77,75,72,69,66,64],"all_points_y":[62,60,55,52,50,49,49,53,58,61,61,61,62,64,66,68,70,73,77,80,80,77,73,70,66,65,64,65,66,61,58,58,58,60,62]},"region_attributes":{"type":"unknown","image_quality":{"good":true,"frontal":true,"good_illumination":true},"leaf":"not_defined"}}],"file_attributes":{"caption":"","public_domain":"no","image_url":""}},"0018.png1644":{"filename":"0018.png","size":1644,"regions":[{"shape_attributes":{"name":"polyline","all_points_x":[64,62,62,62,62,61,58,57,53,51,51,55,57,58,60,61,60,59,60,61,59,56,57,59,62,63,65,66,66,65,64,64,67,69,72,74,76,78,79,80,79,78,76,74,70,69,66,65,64],"all_points_y":[62,61,58,56,54,52,50,49,48,52,56,60,60,60,61,62,64,64,66,67,69,73,76,80,80,80,78,75,72,69,67,66,65,65,66,67,67,66,63,61,57,57,57,57,57,58,60,62,63]},"region_attributes":{"type":"unknown","image_quality":{"good":true,"frontal":true,"good_illumination":true},"leaf":"not_defined"}}],"file_attributes":{"caption":"","public_domain":"no","image_url":""}},"0019.png2130":{"filename":"0019.png","size":2130,"regions":[{"shape_attributes":{"name":"polyline","all_points_x":[62,61,61,61,60,57,54,51,50,49,50,52,55,58,60,61,56,52,50,51,54,55,57,58,59,60,61,62,62,59,57,56,56,57,59,62,64,66,67,65,64,63,64,65,69,74,76,79,82,84,83,81,78,75,72,70,69,66,63,61],"all_points_y":[60,57,52,50,48,45,44,44,47,51,53,56,57,58,60,61,60,61,64,68,69,69,69,68,66,65,63,65,66,68,70,72,75,78,80,80,80,77,72,68,66,64,63,63,63,63,63,64,64,63,56,54,54,54,54,56,58,59,60,59]},"region_attributes":{"type":"unknown","image_quality":{"good":true,"frontal":true,"good_illumination":true},"leaf":"not_defined"}}],"file_attributes":{"caption":"","public_domain":"no","image_url":""}},"0020.png2576":{"filename":"0020.png","size":2576,"regions":[{"shape_attributes":{"name":"polyline","all_points_x":[63,61,61,62,60,59,57,54,52,50,51,53,55,57,59,60,61,58,55,53,49,46,44,43,44,44,47,50,53,55,57,57,60,61,60,58,56,57,58,61,64,66,66,65,64,64,66,70,72,75,77,79,82,84,86,87,86,83,79,74,70,67,64,63],"all_points_y":[59,57,53,50,46,43,42,42,44,47,52,54,56,56,58,59,60,61,60,59,59,60,61,64,66,68,70,71,72,72,69,66,65,65,67,69,73,77,79,81,80,77,70,68,65,63,63,63,63,64,64,66,67,66,63,59,56,53,52,53,56,59,59,59]},"region_attributes":{"type":"unknown","image_quality":{"good":true,"frontal":true,"good_illumination":true},"leaf":"not_defined"}}],"file_attributes":{"caption":"","public_domain":"no","image_url":""}},"0021.png2893":{"filename":"0021.png","size":2893,"regions":[{"shape_attributes":{"name":"polyline","all_points_x":[61,59,55,52,51,52,55,58,61,62,62,61,61,62,64,65,65,65,70,74,77,80,84,86,88,89,90,89,86,84,80,78,73,71,67,64,63,64,66,66,65,64,62,61,57,55,54,54,55,56,57,59,61,61,58,56,56,55,53,50,46,43,41,37,35,33,33,33,41,45,52,54,57,59,60,61,61],"all_points_y":[59,56,54,51,46,43,41,41,44,50,53,56,58,56,56,57,59,60,58,54,53,53,54,57,58,60,63,64,67,67,67,65,65,64,63,63,64,67,70,73,76,78,80,82,80,79,76,73,71,70,68,67,65,65,65,66,68,70,71,71,70,70,70,72,71,69,66,63,60,62,62,62,60,60,60,59,59]},"region_attributes":{"type":"unknown","image_quality":{"good":true,"frontal":true,"good_illumination":true},"leaf":"not_defined"}}],"file_attributes":{"caption":"","public_domain":"no","image_url":""}},"0022.png2840":{"filename":"0022.png","size":2840,"regions":[{"shape_attributes":{"name":"polyline","all_points_x":[68,70,69,67,66,64,64,63,61,59,57,55,54,55,58,61,63,62,60,58,55,54,51,48,45,42,40,35,34,32,32,33,36,41,46,49,53,56,57,57,57,60,62,63,62,60,58,57,58,59,60,62,64,66,67,67,67,66,66,69,72,74,76,79,81,83,85,87,88,89,88,86,80,78,76,75,71,70,68],"all_points_y":[62,58,55,53,52,53,49,46,45,45,45,47,51,54,57,58,59,62,62,63,65,65,66,66,67,67,67,68,68,69,70,72,74,75,75,75,75,75,74,72,70,69,68,67,69,70,72,75,79,82,83,84,84,82,79,74,71,66,66,66,66,67,67,68,69,70,72,70,67,64,61,58,55,55,56,57,60,61,62]},"region_attributes":{"type":"unknown","image_quality":{"good":true,"frontal":true,"good_illumination":true},"leaf":"not_defined"}}],"file_attributes":{"caption":"","public_domain":"no","image_url":""}},"0023.png3568":{"filename":"0023.png","size":3568,"regions":[{"shape_attributes":{"name":"polyline","all_points_x":[73,75,76,77,77,77,73,70,67,65,64,63,61,57,55,54,54,56,59,62,62,61,57,56,54,48,44,36,30,27,24,23,24,31,35,39,42,46,49,53,54,55,55,57,60,60,57,57,57,58,61,63,66,68,67,67,65,66,71,76,80,82,84,86,90,93,93,92,92,91,89,87,85,80,77,73],"all_points_y":[62,59,54,49,46,44,43,43,44,46,50,48,45,45,45,48,52,55,58,60,62,64,64,64,66,69,71,72,72,72,73,76,78,79,80,80,78,78,79,79,77,73,72,71,70,73,75,79,81,84,85,85,85,81,76,74,68,67,67,68,69,69,70,72,72,71,68,65,63,60,58,56,56,56,59,62]},"region_attributes":{"type":"unknown","image_quality":{"good":true,"frontal":true,"good_illumination":true},"leaf":"not_defined"}}],"file_attributes":{"caption":"","public_domain":"no","image_url":""}},"0028.png864":{"filename":"0028.png","size":864,"regions":[{"shape_attributes":{"name":"polyline","all_points_x":[62,62,62,63,64,64,65,66,67,69,71,73,74,74,71,67,65,64,62,59,57,53,51,51,53,55,58,60,62],"all_points_y":[63,61,60,59,60,62,63,63,62,62,62,62,65,67,69,69,65,65,65,70,71,71,70,68,65,64,63,63,63]},"region_attributes":{"type":"unknown","image_quality":{"good":true,"frontal":true,"good_illumination":true},"leaf":"not_defined"}}],"file_attributes":{"caption":"","public_domain":"no","image_url":""}},"0029.png1186":{"filename":"0029.png","size":1186,"regions":[{"shape_attributes":{"name":"polyline","all_points_x":[65,65,66,66,65,62,60,60,60,61,63,62,59,55,53,51,51,52,54,58,61,62,62,64,65,70,72,76,77,77,73,70,68,67,65],"all_points_y":[63,61,60,58,56,55,56,58,60,61,63,65,65,65,66,69,72,73,74,74,71,68,66,66,65,70,70,70,68,64,62,62,63,63,63]},"region_attributes":{"type":"unknown","image_quality":{"good":true,"frontal":true,"good_illumination":true},"leaf":"not_defined"}}],"file_attributes":{"caption":"","public_domain":"no","image_url":""}},"0030.png1450":{"filename":"0030.png","size":1450,"regions":[{"shape_attributes":{"name":"polyline","all_points_x":[63,62,60,58,58,59,61,63,65,65,65,64,64,65,68,70,72,74,76,78,79,80,79,77,75,72,69,67,66,65,63,62,61,60,56,52,50,49,49,49,50,51,52,53,54,56,58,59,61,62,62],"all_points_y":[65,62,60,58,54,53,52,52,52,54,56,59,61,63,63,61,61,61,61,62,64,66,68,70,71,71,69,66,65,67,67,67,69,73,77,77,76,74,72,71,69,68,67,67,66,66,66,66,66,65,65]},"region_attributes":{"type":"unknown","image_quality":{"good":true,"frontal":true,"good_illumination":true},"leaf":"not_defined"}}],"file_attributes":{"caption":"","public_domain":"no","image_url":""}},"0031.png1601":{"filename":"0031.png","size":1601,"regions":[{"shape_attributes":{"name":"polyline","all_points_x":[66,65,65,66,66,65,63,59,57,57,59,63,62,59,55,51,49,48,48,50,54,57,58,59,59,63,64,67,67,71,73,76,79,80,80,80,79,77,75,73,70,67,66],"all_points_y":[64,61,57,55,53,51,49,49,50,59,61,64,66,66,66,68,71,73,75,77,78,77,76,73,71,67,69,69,67,71,72,71,70,69,66,64,63,62,61,61,62,63,64]},"region_attributes":{"type":"unknown","image_quality":{"good":true,"frontal":true,"good_illumination":true},"leaf":"not_defined"}}],"file_attributes":{"caption":"","public_domain":"no","image_url":""}},"0032.png2052":{"filename":"0032.png","size":2052,"regions":[{"shape_attributes":{"name":"polyline","all_points_x":[63,63,63,63,64,64,61,56,54,53,53,53,54,56,58,59,60,59,56,52,49,45,44,47,50,54,56,57,58,60,60,61,60,60,62,65,67,69,69,66,64,65,67,68,71,75,79,80,80,78,75,72,69,67,65,63],"all_points_y":[65,60,57,53,48,45,43,44,45,48,51,54,56,58,60,62,65,66,67,67,68,71,74,78,78,77,74,71,69,68,66,71,74,76,78,78,78,74,71,68,67,66,67,69,72,72,70,68,64,63,62,62,62,63,64,65]},"region_attributes":{"type":"unknown","image_quality":{"good":true,"frontal":true,"good_illumination":true},"leaf":"not_defined"}}],"file_attributes":{"caption":"","public_domain":"no","image_url":""}},"0033.png2608":{"filename":"0033.png","size":2608,"regions":[{"shape_attributes":{"name":"polyline","all_points_x":[59,59,58,56,54,52,53,56,58,60,63,66,65,64,63,63,63,64,67,69,72,73,75,78,79,80,79,77,73,70,68,66,64,64,68,72,69,65,62,60,60,59,59,59,59,60,60,60,58,58,57,56,54,52,50,47,44,42,42,45,49,58,59,59],"all_points_y":[65,62,60,57,56,52,48,43,42,41,42,45,49,53,57,62,64,65,63,62,61,61,61,62,63,67,71,72,73,72,69,67,66,68,71,75,83,85,85,84,82,80,78,77,75,72,71,68,68,70,72,74,76,77,78,78,77,75,71,68,66,67,65,65]},"region_attributes":{"type":"unknown","image_quality":{"good":true,"frontal":true,"good_illumination":true},"leaf":"not_defined"}}],"file_attributes":{"caption":"","public_domain":"no","image_url":""}},"0034.png2956":{"filename":"0034.png","size":2956,"regions":[{"shape_attributes":{"name":"polyline","all_points_x":[63,63,63,63,64,65,67,66,63,61,55,53,53,53,54,55,56,58,59,59,56,55,56,57,58,55,53,50,47,45,43,42,41,43,46,50,52,58,60,60,61,62,62,61,60,60,61,63,65,70,72,71,70,70,70,70,70,68,66,65,65,65,67,68,72,76,79,80,80,78,76,74,71,67,64,63],"all_points_y":[65,61,57,56,53,50,45,42,39,39,44,46,48,51,54,56,57,59,60,63,63,65,66,66,66,66,66,66,66,66,67,69,72,76,77,77,75,68,67,72,74,77,80,84,85,87,92,93,95,96,93,90,87,84,80,77,74,72,72,69,68,66,69,70,73,73,72,69,67,64,63,63,62,64,65,65]},"region_attributes":{"type":"unknown","image_quality":{"good":true,"frontal":true,"good_illumination":true},"leaf":"not_defined"}}],"file_attributes":{"caption":"","public_domain":"no","image_url":""}},"0035.png2930":{"filename":"0035.png","size":2930,"regions":[{"shape_attributes":{"name":"polyline","all_points_x":[66,66,66,68,69,71,71,68,65,62,59,57,55,55,56,58,59,61,62,62,58,53,52,52,50,48,46,44,45,47,51,53,57,59,61,63,62,63,65,66,66,67,67,68,68,69,71,75,75,74,74,75,75,72,70,68,68,70,72,74,77,80,84,84,83,81,77,74,66],"all_points_y":[63,60,57,52,46,43,41,39,39,39,41,44,47,50,52,54,56,57,59,60,59,60,62,64,64,64,66,68,72,73,74,73,71,67,65,65,68,71,73,77,80,84,87,91,94,96,96,93,90,84,79,75,72,71,70,67,64,67,69,70,71,71,69,66,62,61,61,61,63]},"region_attributes":{"type":"unknown","image_quality":{"good":true,"frontal":true,"good_illumination":true},"leaf":"not_defined"}}],"file_attributes":{"caption":"","public_domain":"no","image_url":""}},"0036.png3702":{"filename":"0036.png","size":3702,"regions":[{"shape_attributes":{"name":"polyline","all_points_x":[63,59,56,54,50,47,45,44,45,47,49,47,45,43,43,45,49,53,58,61,62,56,56,59,64,68,72,72,70,69,66,66,66,70,73,76,81,83,85,85,80,76,74,73,71,70,70,71,71,71,73,76,78,79,78,78,80,79,77,77,77,73,72,72,73,71,67,65,64,64,63],"all_points_y":[66,67,71,73,74,74,72,69,66,65,64,62,61,58,54,52,51,51,52,54,55,48,43,40,37,36,37,43,46,52,58,61,62,62,61,60,60,61,64,68,71,71,69,68,68,68,70,71,72,73,73,73,74,77,82,86,91,96,99,102,104,105,103,97,92,85,76,73,71,68,66]},"region_attributes":{"type":"unknown","image_quality":{"good":true,"frontal":true,"good_illumination":true},"leaf":"not_defined"}}],"file_attributes":{"caption":"","public_domain":"no","image_url":""}},"0041.png908":{"filename":"0041.png","size":908,"regions":[{"shape_attributes":{"name":"polyline","all_points_x":[63,61,60,61,63,63,63,62,61,63,64,67,68,69,67,65,66,69,71,72,71,69,65,64,64,63,63],"all_points_y":[66,66,65,64,64,64,62,61,57,55,54,54,56,58,63,64,66,68,71,75,77,77,76,73,69,67,66]},"region_attributes":{"type":"unknown","image_quality":{"good":true,"frontal":true,"good_illumination":true},"leaf":"not_defined"}}],"file_attributes":{"caption":"","public_domain":"no","image_url":""}},"0042.png1209":{"filename":"0042.png","size":1209,"regions":[{"shape_attributes":{"name":"polyline","all_points_x":[63,64,62,62,62,63,66,68,69,70,67,65,66,67,71,73,74,74,74,72,71,68,66,65,65,65,64,62,61,60,59,57,56,56,57,58,60,61,63,63,64,64],"all_points_y":[63,61,59,57,55,52,51,51,53,57,60,62,65,66,68,70,71,73,75,77,78,77,75,72,70,66,65,65,67,69,69,68,67,65,63,63,63,63,63,63,61,61]},"region_attributes":{"type":"unknown","image_quality":{"good":true,"frontal":true,"good_illumination":true},"leaf":"not_defined"}}],"file_attributes":{"caption":"","public_domain":"no","image_url":""}},"0043.png1489":{"filename":"0043.png","size":1489,"regions":[{"shape_attributes":{"name":"polyline","all_points_x":[63,64,62,61,64,67,70,70,70,66,65,67,67,69,70,72,74,75,76,76,76,75,72,69,67,66,66,66,66,65,64,62,60,59,57,54,52,52,52,52,53,55,58,59,61,63,64,63],"all_points_y":[63,61,58,55,49,48,50,52,56,61,63,64,65,67,67,68,69,71,73,76,78,79,79,79,76,75,73,71,69,67,66,67,68,69,70,70,69,67,64,63,62,62,63,63,63,63,63,63]},"region_attributes":{"type":"unknown","image_quality":{"good":true,"frontal":true,"good_illumination":true},"leaf":"not_defined"}}],"file_attributes":{"caption":"","public_domain":"no","image_url":""}},"0044.png1654":{"filename":"0044.png","size":1654,"regions":[{"shape_attributes":{"name":"polyline","all_points_x":[64,65,62,62,64,66,69,70,71,71,69,67,66,68,69,68,67,68,70,72,74,77,77,77,77,76,73,70,67,66,66,66,66,65,61,60,58,56,53,50,49,48,49,51,54,58,60,64,64],"all_points_y":[63,60,57,51,49,47,48,50,55,58,60,61,62,62,63,65,65,67,68,69,69,71,74,76,79,80,81,79,76,73,71,69,67,65,67,69,71,71,71,71,71,67,64,62,61,63,63,63,63]},"region_attributes":{"type":"unknown","image_quality":{"good":true,"frontal":true,"good_illumination":true},"leaf":"not_defined"}}],"file_attributes":{"caption":"","public_domain":"no","image_url":""}},"0045.png2124":{"filename":"0045.png","size":2124,"regions":[{"shape_attributes":{"name":"polyline","all_points_x":[67,68,71,74,75,78,78,78,75,72,69,68,67,67,67,67,66,65,63,61,60,59,57,56,55,49,47,45,44,46,49,52,54,56,58,61,64,65,62,62,63,64,68,71,72,72,71,67,66,68,69,71,73,77,78,75,67],"all_points_y":[67,70,70,71,72,76,78,81,84,84,81,80,78,76,74,71,69,67,68,69,70,72,73,74,74,75,74,73,66,64,64,65,65,65,65,65,64,63,59,55,51,49,48,51,54,56,58,62,64,63,62,60,59,61,65,68,67]},"region_attributes":{"type":"unknown","image_quality":{"good":true,"frontal":true,"good_illumination":true},"leaf":"not_defined"}}],"file_attributes":{"caption":"","public_domain":"no","image_url":""}},"0046.png2560":{"filename":"0046.png","size":2560,"regions":[{"shape_attributes":{"name":"polyline","all_points_x":[67,67,69,71,72,71,70,67,64,62,62,62,63,65,65,63,60,56,52,51,47,44,41,41,43,45,47,50,53,56,64,66,66,66,66,68,70,73,77,78,77,73,70,68,67,71,74,80,84,85,85,83,79,75,72,70,68],"all_points_y":[64,62,61,58,55,50,48,48,48,50,54,57,60,63,64,65,65,65,64,64,62,62,66,70,73,74,75,75,76,75,67,68,71,74,78,82,85,86,84,81,76,72,71,69,67,68,69,69,67,66,62,59,58,57,60,61,63]},"region_attributes":{"type":"unknown","image_quality":{"good":true,"frontal":true,"good_illumination":true},"leaf":"not_defined"}}],"file_attributes":{"caption":"","public_domain":"no","image_url":""}},"0047.png2847":{"filename":"0047.png","size":2847,"regions":[{"shape_attributes":{"name":"polyline","all_points_x":[65,65,63,63,65,66,69,72,74,73,70,67,71,72,73,78,85,91,95,95,90,85,81,72,70,68,69,69,71,74,77,78,75,72,70,68,66,65,66,66,67,67,67,66,65,64,63,63,64,61,59,56,55,53,50,47,43,39,38,42,43,47,49,52,56,58,61,65],"all_points_y":[65,61,58,52,48,47,47,49,53,57,60,63,62,60,58,58,58,57,58,62,67,68,66,67,68,69,71,72,73,74,78,82,86,87,86,84,82,79,76,74,72,70,70,72,72,72,69,68,66,69,70,72,74,75,75,75,72,67,65,61,61,61,62,64,64,65,65,65]},"region_attributes":{"type":"unknown","image_quality":{"good":true,"frontal":true,"good_illumination":true},"leaf":"not_defined"}}],"file_attributes":{"caption":"","public_domain":"no","image_url":""}},"0048.png2824":{"filename":"0048.png","size":2824,"regions":[{"shape_attributes":{"name":"polyline","all_points_x":[72,71,65,70,69,67,64,61,63,63,54,51,38,41,57],"all_points_y":[53,58,61,53,46,44,44,48,60,61,62,60,63,70,69]},"region_attributes":{"type":"unknown","image_quality":{"good":true,"frontal":true,"good_illumination":true},"leaf":"not_defined"}},{"shape_attributes":{"name":"polyline","all_points_x":[72,76,80,83,89,93,96,96,91,86,82,75,70,68,65,67,67,70,72,74,74,71,69,64,63,62,59,61,64,58,56,55,53,49,45,41,40,39,43,44,46,52,61,61,63,63],"all_points_y":[53,52,53,53,53,54,57,60,61,61,61,63,65,66,66,68,70,71,74,77,80,82,84,80,77,76,71,65,63,67,69,72,73,73,72,70,66,63,57,57,57,61,63,63,61,61]},"region_attributes":{"type":"unknown","image_quality":{"good":true,"frontal":true,"good_illumination":true},"leaf":"not_defined"}}],"file_attributes":{"caption":"","public_domain":"no","image_url":""}},"0049.png3535":{"filename":"0049.png","size":3535,"regions":[{"shape_attributes":{"name":"polyline","all_points_x":[62,63,61,61,64,68,71,71,69,68,68,72,74,75,79,84,87,91,95,98,103,105,103,100,94,88,79,75,71,68,66,66,69,73,75,74,69,67,64,63,62,58,52,50,52,53,56,61,52,49,43,40,38,36,37,38,46,55,59,62],"all_points_y":[61,57,53,46,43,43,48,53,55,57,58,56,54,49,49,50,49,48,49,49,50,52,55,56,56,56,60,62,64,65,65,68,71,73,80,84,84,84,79,82,84,86,85,81,75,71,65,64,68,72,72,69,66,60,56,56,58,60,61,61]},"region_attributes":{"type":"unknown","image_quality":{"good":true,"frontal":true,"good_illumination":true},"leaf":"not_defined"}}],"file_attributes":{"caption":"","public_domain":"no","image_url":""}},"0054.png879":{"filename":"0054.png","size":879,"regions":[{"shape_attributes":{"name":"polyline","all_points_x":[66,66,67,69,71,72,74,75,76,77,75,72,69,67,67,65,63,62,60,56,54,53,54,56,58,61,62,63,64,64,65,66,66,67],"all_points_y":[61,63,64,64,64,64,65,66,67,69,71,71,70,67,65,64,64,67,68,68,67,65,63,62,62,62,63,63,63,60,60,60,60,60]},"region_attributes":{"type":"unknown","image_quality":{"good":true,"frontal":true,"good_illumination":true},"leaf":"not_defined"}}],"file_attributes":{"caption":"","public_domain":"no","image_url":""}},"0055.png1213":{"filename":"0055.png","size":1213,"regions":[{"shape_attributes":{"name":"polyline","all_points_x":[63,63,62,62,64,66,68,68,66,65,65,67,68,72,76,77,78,77,76,74,72,69,67,66,64,63,62,60,59,57,55,53,51,51,52,55,57,59,60,62,63],"all_points_y":[64,61,60,58,56,55,57,61,62,62,64,65,65,65,67,69,71,73,74,74,74,72,70,66,65,65,65,67,69,70,70,69,67,64,63,62,62,63,63,64,64]},"region_attributes":{"type":"unknown","image_quality":{"good":true,"frontal":true,"good_illumination":true},"leaf":"not_defined"}}],"file_attributes":{"caption":"","public_domain":"no","image_url":""}},"0056.png1462":{"filename":"0056.png","size":1462,"regions":[{"shape_attributes":{"name":"polyline","all_points_x":[63,64,64,63,63,63,63,64,67,69,69,69,69,66,66,67,70,73,75,77,79,79,78,75,73,70,69,68,67,66,66,65,64,63,63,61,59,57,53,51,50,48,48,51,54,57,59,60,63],"all_points_y":[64,61,60,59,58,56,54,52,52,52,56,58,60,62,64,65,66,66,66,68,71,74,76,76,76,75,74,72,69,67,66,68,68,66,65,67,69,70,70,70,69,66,64,62,61,61,62,63,64]},"region_attributes":{"type":"unknown","image_quality":{"good":true,"frontal":true,"good_illumination":true},"leaf":"not_defined"}}],"file_attributes":{"caption":"","public_domain":"no","image_url":""}},"0057.png1612":{"filename":"0057.png","size":1612,"regions":[{"shape_attributes":{"name":"polyline","all_points_x":[63,63,62,64,67,71,71,71,70,67,65,65,66,69,73,76,78,79,80,78,75,71,70,69,67,65,64,63,61,61,59,57,55,53,51,49,48,49,53,56,59,61,63],"all_points_y":[64,57,53,49,49,49,53,57,61,62,64,65,65,66,66,67,69,70,75,77,78,76,75,71,68,67,69,69,67,67,69,70,71,71,70,69,66,63,61,61,63,64,64]},"region_attributes":{"type":"unknown","image_quality":{"good":true,"frontal":true,"good_illumination":true},"leaf":"not_defined"}}],"file_attributes":{"caption":"","public_domain":"no","image_url":""}},"0058.png2063":{"filename":"0058.png","size":2063,"regions":[{"shape_attributes":{"name":"polyline","all_points_x":[68,69,71,74,75,75,70,67,66,64,63,64,65,65,65,66,65,65,63,60,57,53,50,48,48,48,50,53,57,60,62,64,64,62,60,59,59,62,65,67,68,67,67,67,67,69,70,71,74,76,79,81,83,84,84,82,80,78,76,73,71,69,68,69],"all_points_y":[65,62,59,57,55,48,44,44,44,46,47,50,52,56,58,62,65,66,64,63,62,62,64,65,68,70,72,73,72,70,67,66,67,69,70,73,76,78,78,76,74,71,69,67,66,68,70,73,77,78,79,78,77,75,71,70,68,68,67,67,67,67,65,62]},"region_attributes":{"type":"unknown","image_quality":{"good":true,"frontal":true,"good_illumination":true},"leaf":"not_defined"}}],"file_attributes":{"caption":"","public_domain":"no","image_url":""}},"0059.png2602":{"filename":"0059.png","size":2602,"regions":[{"shape_attributes":{"name":"polyline","all_points_x":[65,65,64,62,62,66,69,71,76,76,75,71,70,68,67,68,73,75,79,82,85,86,83,79,76,75,73,72,71,70,69,67,68,69,68,68,67,63,59,57,56,56,58,61,64,64,61,59,55,50,48,47,53,57,60,61,64,65],"all_points_y":[65,56,51,47,44,42,41,42,47,52,56,58,60,62,65,67,68,67,67,67,70,74,77,78,78,77,75,72,71,70,68,67,72,74,81,83,85,85,83,80,77,75,72,71,68,66,69,71,73,72,69,65,62,62,62,64,64,64]},"region_attributes":{"type":"unknown","image_quality":{"good":true,"frontal":true,"good_illumination":true},"leaf":"not_defined"}}],"file_attributes":{"caption":"","public_domain":"no","image_url":""}},"0060.png2968":{"filename":"0060.png","size":2968,"regions":[{"shape_attributes":{"name":"polyline","all_points_x":[68,70,74,75,74,68,64,61,61,62,63,64,65,65,65,64,61,59,56,52,47,47,47,48,51,55,62,63,63,62,58,58,58,57,57,60,63,66,67,68,67,67,66,66,66,67,68,68,68,69,70,71,72,75,78,81,87,87,87,86,84,81,78,74,72,69,72,72,72,72,69,68],"all_points_y":[63,60,55,48,44,38,38,41,46,49,54,56,60,63,65,66,65,63,62,63,67,68,70,72,74,74,69,67,70,72,73,76,83,91,94,96,95,92,89,86,84,81,78,77,75,73,71,70,68,68,69,70,71,75,77,78,74,72,69,68,66,66,66,66,67,66,66,65,64,63,63,62]},"region_attributes":{"type":"unknown","image_quality":{"good":true,"frontal":true,"good_illumination":true},"leaf":"not_defined"}}],"file_attributes":{"caption":"","public_domain":"no","image_url":""}},"0061.png2934":{"filename":"0061.png","size":2934,"regions":[{"shape_attributes":{"name":"polyline","all_points_x":[62,62,61,60,58,57,58,61,63,66,69,71,71,72,73,73,71,69,67,66,66,65,67,70,73,75,76,76,76,78,79,81,82,83,81,80,78,77,75,72,71,70,70,69,67,66,66,65,63,62,61,61,61,61,60,60,60,59,57,54,54,54,54,54,54,53,53,53,53,54,55,56,58,59,60,61,55,53,51,48,47,46,45,44,45,47,49,51,53,56,59,61,62],"all_points_y":[63,57,52,48,45,44,41,40,39,40,41,44,46,49,50,52,54,56,58,59,60,61,60,59,60,61,62,63,65,64,64,65,66,69,72,73,74,74,74,72,71,69,68,66,66,66,68,71,73,80,81,84,86,88,91,95,95,97,97,94,92,88,85,84,82,79,76,73,72,72,72,71,71,68,67,64,70,70,71,70,70,69,67,64,63,61,61,61,61,61,63,63,62]},"region_attributes":{"type":"unknown","image_quality":{"good":true,"frontal":true,"good_illumination":true},"leaf":"not_defined"}}],"file_attributes":{"caption":"","public_domain":"no","image_url":""}},"0062.png3719":{"filename":"0062.png","size":3719,"regions":[{"shape_attributes":{"name":"polyline","all_points_x":[65,65,63,61,59,58,56,56,56,56,56,56,54,50,49,50,49,49,49,50,49,50,54,56,58,57,55,54,50,48,45,43,43,44,46,48,51,53,55,59,61,61,61,59,56,56,61,65,67,69,72,72,71,67,64,69,70,72,74,74,75,77,81,83,85,86,85,83,81,79,75,78,79,81,82,83,83,83,81,75,73,70,68,66,65],"all_points_y":[66,70,73,76,81,84,87,89,92,95,99,102,104,105,99,98,95,90,85,83,76,74,73,73,68,67,69,70,71,71,69,67,64,62,61,61,61,61,62,63,63,60,57,47,43,38,36,36,38,40,43,46,50,53,56,53,52,52,52,52,52,51,51,52,53,57,60,61,63,64,65,65,65,66,67,68,71,73,74,73,72,69,66,66,66]},"region_attributes":{"type":"unknown","image_quality":{"good":true,"frontal":true,"good_illumination":true},"leaf":"not_defined"}}],"file_attributes":{"caption":"","public_domain":"no","image_url":""}},"0067.png871":{"filename":"0067.png","size":871,"regions":[{"shape_attributes":{"name":"polyline","all_points_x":[64,65,66,68,70,73,75,74,73,70,66,66,64,64,64,62,62,62,61,59,57,56,53,52,51,52,54,57,60,61,62,64,64],"all_points_y":[64,63,61,60,59,59,61,64,66,67,65,65,65,67,68,68,66,64,64,64,65,65,63,61,58,57,56,57,59,61,63,64,64]},"region_attributes":{"type":"unknown","image_quality":{"good":true,"frontal":true,"good_illumination":true},"leaf":"not_defined"}}],"file_attributes":{"caption":"","public_domain":"no","image_url":""}},"0068.png1191":{"filename":"0068.png","size":1191,"regions":[{"shape_attributes":{"name":"polyline","all_points_x":[64,62,61,59,57,54,52,51,50,51,52,54,57,60,61,63,63,62,60,59,59,60,61,63,65,66,66,65,65,65,67,69,71,74,76,77,77,75,72,70,69,68,67,66,65,64],"all_points_y":[63,61,58,56,54,54,54,55,57,60,61,62,63,63,63,64,64,66,67,68,71,72,73,73,72,71,68,66,65,65,64,66,66,66,65,64,60,59,58,59,60,61,62,62,63,63]},"region_attributes":{"type":"unknown","image_quality":{"good":true,"frontal":true,"good_illumination":true},"leaf":"not_defined"}}],"file_attributes":{"caption":"","public_domain":"no","image_url":""}},"0069.png1476":{"filename":"0069.png","size":1476,"regions":[{"shape_attributes":{"name":"polyline","all_points_x":[65,64,65,65,66,66,65,64,62,59,58,58,58,59,60,62,62,61,59,55,54,51,50,48,50,52,53,55,57,59,60,60,60,61,62,62,64,65,65,65,65,66,68,69,70,72,73,75,76,78,79,80,80,79,75,73,71,69,67,67,65],"all_points_y":[65,67,69,70,73,74,76,77,77,77,74,72,70,69,68,66,64,62,62,62,62,61,59,55,53,52,52,52,52,54,55,56,58,59,61,62,61,61,62,62,63,63,62,60,58,58,58,58,58,59,60,63,64,65,67,67,67,66,66,65,65]},"region_attributes":{"type":"unknown","image_quality":{"good":true,"frontal":true,"good_illumination":true},"leaf":"not_defined"}}],"file_attributes":{"caption":"","public_domain":"no","image_url":""}},"0070.png1612":{"filename":"0070.png","size":1612,"regions":[{"shape_attributes":{"name":"polyline","all_points_x":[63,64,65,66,66,66,68,70,73,75,76,78,79,80,80,80,79,78,76,73,69,68,66,65,65,65,65,66,67,67,66,63,61,58,57,57,57,57,61,62,63,62,61,58,56,53,51,48,48,51,53,55,57,58,59,59,60,61,61,62,63],"all_points_y":[61,59,59,60,61,62,61,59,57,57,58,58,59,60,61,62,63,65,66,66,65,64,64,64,66,68,71,73,73,75,77,79,80,79,78,75,73,70,66,66,64,62,62,62,62,62,60,56,53,51,51,51,52,53,54,57,58,58,59,61,61]},"region_attributes":{"type":"unknown","image_quality":{"good":true,"frontal":true,"good_illumination":true},"leaf":"not_defined"}}],"file_attributes":{"caption":"","public_domain":"no","image_url":""}},"0071.png2101":{"filename":"0071.png","size":2101,"regions":[{"shape_attributes":{"name":"polyline","all_points_x":[61,61,61,60,61,64,66,68,69,69,69,68,65,64,64,66,67,69,70,72,75,76,79,80,80,80,79,77,73,70,67,66,63,63,63,63,63,63,64,64,64,64,62,58,55,53,54,53,53,53,54,60,60,60,58,53,51,49,47,44,44,44,46,50,53,55,56,57,58,60,61],"all_points_y":[61,58,56,54,51,50,50,51,53,55,57,59,60,61,62,60,59,57,56,56,56,56,58,59,61,63,64,65,66,66,65,64,63,64,65,69,72,75,76,79,80,82,85,84,84,82,80,78,76,74,72,65,64,62,61,61,61,61,59,57,54,52,50,50,50,52,54,56,57,61,61]},"region_attributes":{"type":"unknown","image_quality":{"good":true,"frontal":true,"good_illumination":true},"leaf":"not_defined"}}],"file_attributes":{"caption":"","public_domain":"no","image_url":""}}}